gdtf/__init__.py
gdtf/_core.py
gdtf-0.1.1.dist-info/METADATA
gdtf-0.1.1.dist-info/WHEEL
gdtf-0.1.1.dist-info/RECORD
